datamonitor/__init__.py
datamonitor/__main__.py
datamonitor/cli.py
datamonitor/datamonitor.py
datamonitor-0.0.5.post5.dist-info/AUTHORS.rst
datamonitor-0.0.5.post5.dist-info/LICENSE
datamonitor-0.0.5.post5.dist-info/METADATA
datamonitor-0.0.5.post5.dist-info/WHEEL
datamonitor-0.0.5.post5.dist-info/entry_points.txt
datamonitor-0.0.5.post5.dist-info/top_level.txt
datamonitor-0.0.5.post5.dist-info/RECORD
