Metadata-Version: 2.1
Name: datamonitor
Version: 0.0.5.post5
Summary: Python utility to monitor metadata KPI
Home-page: https://github.com/infra-helpers/induction-monitoring/python
Author: Denis Arnaud
Author-email: denis.arnaud_fedora@m4x.org
License: MIT
Project-URL: Documentation, https://datamonitoring.readthedocs.io/en/latest/
Project-URL: Changelog, https://datamonitoring.readthedocs.io/en/latest/changelog.html
Project-URL: Issue Tracker, https://github.com/infra-helpers/induction-monitoring/issues
Keywords: data,monitoring,data-monitoring,quality,quality-assurance,qa,kpi,metric,sensor
Platform: UNKNOWN
Classifier: Development Status :: 5 - Production/Stable
Classifier: Intended Audience :: Developers
Classifier: License :: OSI Approved :: MIT License
Classifier: Operating System :: Unix
Classifier: Operating System :: POSIX
Classifier: Operating System :: Microsoft :: Windows
Classifier: Programming Language :: Python
Classifier: Programming Language :: Python :: 3
Classifier: Programming Language :: Python :: 3.6
Classifier: Programming Language :: Python :: 3.7
Classifier: Programming Language :: Python :: 3.8
Classifier: Programming Language :: Python :: Implementation :: CPython
Classifier: Topic :: Utilities
Requires-Python: >=2.7, !=3.0.*, !=3.1.*, !=3.2.*, !=3.3.*, !=3.4.*
Requires-Dist: elasticsearch
Requires-Dist: elasticmock
